{
    "KPlugin": {
        "Category": "Language Support",
        "Description": "QML/JS language support (based on qmljs from QtCreator)",
        "Description[ar]": "دعم لغة QML/JS (المستند إلى qmljs من QtCreator)",
        "Description[az]": "QML/JS dil dəstəyi (r-Creator'dan qmljs əsasında)",
        "Description[ca@valencia]": "Implementació dels llenguatges QML/JS (basats en «qmljs» del QtCreator)",
        "Description[ca]": "Implementació dels llenguatges QML/JS (basats en el «qmljs» del QtCreator)",
        "Description[de]": "Sprachunterstützung für QML/JS auf der Grundlage von qmljs von QtCreator",
        "Description[el]": "Υποστήριξη γλώσσας QML/JS (με βάση το qmljs από το QtCreator)",
        "Description[en_GB]": "QML/JS language support (based on qmljs from QtCreator)",
        "Description[eo]": "QML/JS-lingva subteno (surbaze de qmljs de QtCreator)",
        "Description[es]": "Implementación del lenguaje QML/JS (basado en qmljs de QtCreator)",
        "Description[et]": "QML/JS keele toetus (põhineb QtCreatori qmljs'il)",
        "Description[eu]": "QML/JS lengoaiaren euskarria («QtCreator»en «qmljs»en oinarrituta)",
        "Description[fi]": "QML/JS-kielituki (perustuu QtCreatorin qmljs:ään)",
        "Description[fr]": "Prise en charge du langage QML / JS (utilisant le module « qmljs » de QtCreator)",
        "Description[gl]": "Compatibilidade con QML/JS (baseada en qmljs de QtCreator)",
        "Description[he]": "תמיכה בשפות QML/JS (מבוסס על qmljs מבית QtCreator)",
        "Description[it]": "Supporto al linguaggio QML/JS (basato su qmljs di QtCreator)",
        "Description[ka]": "QML/JS ენის მხარდაჭერა (დაფუძნებულია qmljs-ზე QtCreator-დან)",
        "Description[ko]": "QML/JS 언어 지원(QtCreator의 qmljs 기반)",
        "Description[nl]": "Taalondersteuning voor QML/JS (gebaseerd op qmljs uit QtCreator)",
        "Description[pl]": "Obsługa języka QML/JS (oparta na qmljs z QtCreator)",
        "Description[pt]": "Suporte para a linguagem QML/JS (baseado no 'qmljs' do QtCreator)",
        "Description[pt_BR]": "Suporte para a linguagem QML/JS (baseado no 'qmljs' do QtCreator)",
        "Description[ru]": "Поддержка языка QML/JS (на основе qmljs от QtCreator)",
        "Description[sa]": "QML/JS भाषासमर्थनम् (QtCreator तः qmljs इत्यस्य आधारेण)",
        "Description[sk]": "Podpora jazyka QML/JS (založená na qmljs z QtCreator-a)",
        "Description[sl]": "Podpora jeziku QML/JS (osnovano na qmljs od QtCreator-ja)",
        "Description[sv]": "QML/JS språkstöd (baserat på qmljs från QtCreator)",
        "Description[tr]": "QML/JS dil desteği (QtCreator’dan qmljs tabanlı)",
        "Description[uk]": "Підтримка мови QML/JS (на основі qmljs з QtCreator)",
        "Description[zh_CN]": "QML/JS 语言支持 (基于 QtCreator 的 qmljs)",
        "Description[zh_TW]": "QML/JS 語言支援（基於來自 QtCreator 的 qmljs）",
        "Icon": "text-x-qml",
        "Id": "kdevqmljs",
        "License": "GPL",
        "Name": "QML Support",
        "Name[ar]": "دعم QML",
        "Name[az]": "QML dəstəyi",
        "Name[ca@valencia]": "Implementació de QML",
        "Name[ca]": "Implementació del QML",
        "Name[cs]": "Podpora QML",
        "Name[de]": "Unterstützung für QML",
        "Name[el]": "Υποστήριξη QML",
        "Name[en_GB]": "QML Support",
        "Name[eo]": "QML-subteno",
        "Name[es]": "Implementación de QML",
        "Name[et]": "QML-i toetus",
        "Name[eu]": "QMLeren euskarria",
        "Name[fi]": "QML-tuki",
        "Name[fr]": "Prise en charge de QML",
        "Name[gl]": "Compatibilidade con QML",
        "Name[hu]": "QML támogatás",
        "Name[it]": "Supporto per QML",
        "Name[ka]": "QML-ის მხარდაჭერა",
        "Name[ko]": "QML 지원",
        "Name[nl]": "Ondersteuning voor QML",
        "Name[pl]": "Obsługa QML",
        "Name[pt]": "Suporte para o QML",
        "Name[pt_BR]": "Suporte à QML",
        "Name[ru]": "Поддержка QML",
        "Name[sa]": "QML समर्थन",
        "Name[sk]": "Podpora QML",
        "Name[sl]": "Podpora za QML",
        "Name[sv]": "QML-stöd",
        "Name[tr]": "QML Desteği",
        "Name[uk]": "Підтримка QML",
        "Name[zh_CN]": "QML 支持",
        "Name[zh_TW]": "QML 支援"
    },
    "X-KDevelop-Interfaces": [
        "ILanguageSupport"
    ],
    "X-KDevelop-Languages": [
        "QML/JS",
        "JavaScript"
    ],
    "X-KDevelop-Mode": "NoGUI",
    "X-KDevelop-SupportedMimeTypes": [
        "text/x-qml",
        "application/javascript",
        "text/javascript"
    ]
}
