{
    "KPlugin": {
        "Authors": [
            {
                "Name": "Robert Gruber"
            }
        ], 
        "Category": "Version Control", 
        "Description": "This plugin integrates CVS to KDevelop", 
        "Icon": "cervisia", 
        "Id": "kdevcvs", 
        "License": "GPL", 
        "Name": "CVS Support", 
        "ServiceTypes": [
            "KDevelop/Plugin"
        ], 
        "Version": "0.1"
    }, 
    "X-KDevelop-Category": "Global", 
    "X-KDevelop-Interfaces": [
        "org.kdevelop.IBasicVersionControl"
    ], 
    "X-KDevelop-Mode": "GUI"
}