{
    "KPlugin": {
        "Category": "Project Management", 
        "Description": "Imports and edits custom make projects", 
        "Icon": "gear", 
        "Id": "KDevCustomMakeManager", 
        "Name": "Custom Makefile Project Manager", 
        "ServiceTypes": [
            "KDevelop/Plugin"
        ]
    }, 
    "X-KDevelop-FileManager": "CustomMake", 
    "X-KDevelop-IRequired": [
        "org.kdevelop.IMakeBuilder", 
        "org.kdevelop.IDefinesAndIncludesManager"
    ], 
    "X-KDevelop-Interfaces": [
        "org.kdevelop.IBuildSystemManager", 
        "org.kdevelop.IProjectFileManager"
    ], 
    "X-KDevelop-Mode": "NoGUI", 
    "X-KDevelop-ProjectFilesFilter": [
        "GNUmakefile", 
        "Makefile", 
        "makefile", 
        "GNUmakefile.*", 
        "Makefile.*", 
        "makefile.*"
    ], 
    "X-KDevelop-ProjectFilesFilterDescription": "Makefiles"
}