{
    "KPlugin": {
        "Authors": [
            {
                "Name": "Miquel Sabaté"
            }
        ], 
        "Category": "Utilities", 
        "Description": "This plugin helps to obtain projects from Github", 
        "Description[ca]": "Aquest connector ajuda a obtenir els projectes des de Github", 
        "Description[de]": "Dieses Modul hilft dabei Github-Projekte zu beziehen", 
        "Description[en_GB]": "This plugin helps to obtain projects from Github", 
        "Description[es]": "Este complemento le ayuda a obtener proyectos de Github", 
        "Description[nl]": "Deze plug-in helpt om projecten uit Github te verkrijgen", 
        "Description[sk]": "Tento modul pomáha získavať projekty z Github", 
        "Description[sv]": "Insticksprogrammet hjälper till att erhålla projekt Github", 
        "Description[uk]": "За допомогою цього додатка можна отримувати проекти з Github", 
        "Description[x-test]": "xxThis plugin helps to obtain projects from Githubxx", 
        "Icon": "kdevgh", 
        "Id": "kdevghprovider", 
        "License": "GPL", 
        "Name": "Github Provider", 
        "Name[ca]": "Proveïdor de Github", 
        "Name[de]": "Github-Provider", 
        "Name[en_GB]": "Github Provider", 
        "Name[es]": "Proveedor de Github", 
        "Name[nl]": "Github-leverancier", 
        "Name[sk]": "Poskytovateľ Github", 
        "Name[sv]": "Github-leverantör", 
        "Name[uk]": "Надавач даних Github", 
        "Name[x-test]": "xxGithub Providerxx", 
        "ServiceTypes": [
            "KDevelop/Plugin"
        ]
    }, 
    "X-KDevelop-Interfaces": [
        "org.kdevelop.IProjectProvider"
    ], 
    "X-KDevelop-Mode": "GUI"
}